ping/__init__.py
ping/__main__.py
simple_ping-0.1.dist-info/LICENSE
simple_ping-0.1.dist-info/METADATA
simple_ping-0.1.dist-info/WHEEL
simple_ping-0.1.dist-info/top_level.txt
simple_ping-0.1.dist-info/RECORD
