Metadata-Version: 2.1
Name: simple-ping
Version: 0.1
Summary: Python ping package
Home-page: https://github.com/nandoabreu/python-ping
Author: Fernando Abreu
License: UNKNOWN
Platform: UNKNOWN
Classifier: Programming Language :: Python :: 3
Classifier: License :: OSI Approved :: MIT License
Classifier: Operating System :: OS Independent
